{
  "text": "Les Art Premiers Au Musée\nSi cette reconnaissance sonne comme un cri de victoire, c'est qu'il marque l'issue d'un combat idéaliste qui n'a fait d'autres victimes que l'arrogance et Les préjugés. Le signal en fut donné par Guillaume Apollinaire en 1909 : « le Louvre devrait recueillir certains chefs d'œuvre exotiques dont l'aspect n'est pas moins émouvant que celui des beaux spécimens de la statutaire occidental. Près d'un siècle plus tard, le vœu du poète est enfin comblé plus d'une centaine de sculptures primitives d'Afrique, d'Asie, d'Océanie et des Amérique, jusqu'alors confinées dans des réserves ethnographiques, prennent place dans le temps de l'Art, jusqu'alors réservé à l'Europe et à ses sources. Cet événement est présenté comme...",
  "words": [
    "Les",
    "Art",
    "Premiers",
    "Au",
    "Musée",
    "Si",
    "cette",
    "reconnaissance",
    "sonne",
    "comme",
    "un",
    "cri",
    "de",
    "victoire,",
    "c&apos;est",
    "qu&apos;il",
    "marque",
    "l&apos;issue",
    "d&apos;un",
    "combat",
    "idéaliste",
    "qui",
    "n&apos;a",
    "fait",
    "d&apos;autres",
    "victimes",
    "que",
    "l&apos;arrogance",
    "et",
    "Les",
    "préjugés.",
    "Le",
    "signal",
    "en",
    "fut",
    "donné",
    "par",
    "Guillaume",
    "Apollinaire",
    "en",
    "1909",
    ":",
    "«",
    "le",
    "Louvre",
    "devrait",
    "recueillir",
    "certains",
    "chefs",
    "d&apos;œuvre",
    "exotiques",
    "dont",
    "l&apos;aspect",
    "n&apos;est",
    "pas",
    "moins",
    "émouvant",
    "que",
    "celui",
    "des",
    "beaux",
    "spécimens",
    "de",
    "la",
    "statutaire",
    "occidental.",
    "Près",
    "d&apos;un",
    "siècle",
    "plus",
    "tard,",
    "le",
    "vœu",
    "du",
    "poète",
    "est",
    "enfin",
    "comblé",
    "plus",
    "d&apos;une",
    "centaine",
    "de",
    "sculptures",
    "primitives",
    "d&apos;Afrique,",
    "d&apos;Asie,",
    "d&apos;Océanie",
    "et",
    "des",
    "Amérique,",
    "jusqu&apos;alors",
    "confinées",
    "dans",
    "des",
    "réserves",
    "ethnographiques,",
    "prennent",
    "place",
    "dans",
    "le",
    "temps",
    "de",
    "l&apos;Art,",
    "jusqu&apos;alors",
    "réservé",
    "à",
    "l&apos;Europe",
    "et",
    "à",
    "ses",
    "sources.",
    "Cet",
    "événement",
    "est",
    "présenté",
    "comme..."
  ],
  "timepoints": [
    {
      "markName": "0",
      "timeSeconds": 0.014999999664723873
    },
    {
      "markName": "1",
      "timeSeconds": 0.25999999046325684
    },
    {
      "markName": "2",
      "timeSeconds": 0.4076249599456787
    },
    {
      "markName": "3",
      "timeSeconds": 0.8175833225250244
    },
    {
      "markName": "4",
      "timeSeconds": 0.9125832915306091
    },
    {
      "markName": "5",
      "timeSeconds": 1.3175833225250244
    },
    {
      "markName": "6",
      "timeSeconds": 1.5275832414627075
    },
    {
      "markName": "7",
      "timeSeconds": 1.797458291053772
    },
    {
      "markName": "8",
      "timeSeconds": 2.5911667346954346
    },
    {
      "markName": "9",
      "timeSeconds": 2.957791566848755
    },
    {
      "markName": "10",
      "timeSeconds": 3.1872081756591797
    },
    {
      "markName": "11",
      "timeSeconds": 3.2672080993652344
    },
    {
      "markName": "12",
      "timeSeconds": 3.4922080039978027
    },
    {
      "markName": "13",
      "timeSeconds": 3.6185832023620605
    },
    {
      "markName": "14",
      "timeSeconds": 4.520082950592041
    },
    {
      "markName": "15",
      "timeSeconds": 4.679582595825195
    },
    {
      "markName": "16",
      "timeSeconds": 4.919582843780518
    },
    {
      "markName": "17",
      "timeSeconds": 5.334915637969971
    },
    {
      "markName": "18",
      "timeSeconds": 5.690623760223389
    },
    {
      "markName": "19",
      "timeSeconds": 5.870956897735596
    },
    {
      "markName": "20",
      "timeSeconds": 6.235957145690918
    },
    {
      "markName": "21",
      "timeSeconds": 7.029290676116943
    },
    {
      "markName": "22",
      "timeSeconds": 7.219290733337402
    },
    {
      "markName": "23",
      "timeSeconds": 7.34929084777832
    },
    {
      "markName": "24",
      "timeSeconds": 7.5354156494140625
    },
    {
      "markName": "25",
      "timeSeconds": 7.906707286834717
    },
    {
      "markName": "26",
      "timeSeconds": 8.407499313354492
    },
    {
      "markName": "27",
      "timeSeconds": 8.577374458312988
    },
    {
      "markName": "28",
      "timeSeconds": 9.233333587646484
    },
    {
      "markName": "29",
      "timeSeconds": 9.273333549499512
    },
    {
      "markName": "30",
      "timeSeconds": 9.373958587646484
    },
    {
      "markName": "31",
      "timeSeconds": 10.877166748046875
    },
    {
      "markName": "32",
      "timeSeconds": 10.987166404724121
    },
    {
      "markName": "33",
      "timeSeconds": 11.422332763671875
    },
    {
      "markName": "34",
      "timeSeconds": 11.507332801818848
    },
    {
      "markName": "35",
      "timeSeconds": 11.713791847229004
    },
    {
      "markName": "36",
      "timeSeconds": 12.038749694824219
    },
    {
      "markName": "37",
      "timeSeconds": 12.263750076293945
    },
    {
      "markName": "38",
      "timeSeconds": 12.655250549316406
    },
    {
      "markName": "39",
      "timeSeconds": 13.339375495910645
    },
    {
      "markName": "40",
      "timeSeconds": 13.434375762939453
    },
    {
      "markName": "41",
      "timeSeconds": 14.418749809265137
    },
    {
      "markName": "42",
      "timeSeconds": 14.418749809265137
    },
    {
      "markName": "43",
      "timeSeconds": 14.78516674041748
    },
    {
      "markName": "44",
      "timeSeconds": 14.925166130065918
    },
    {
      "markName": "45",
      "timeSeconds": 15.39525032043457
    },
    {
      "markName": "46",
      "timeSeconds": 15.751457214355469
    },
    {
      "markName": "47",
      "timeSeconds": 16.264415740966797
    },
    {
      "markName": "48",
      "timeSeconds": 16.668291091918945
    },
    {
      "markName": "49",
      "timeSeconds": 16.943456649780273
    },
    {
      "markName": "50",
      "timeSeconds": 17.253707885742188
    },
    {
      "markName": "51",
      "timeSeconds": 17.865373611450195
    },
    {
      "markName": "52",
      "timeSeconds": 18.085248947143555
    },
    {
      "markName": "53",
      "timeSeconds": 18.511873245239258
    },
    {
      "markName": "54",
      "timeSeconds": 18.651874542236328
    },
    {
      "markName": "55",
      "timeSeconds": 18.844331741333008
    },
    {
      "markName": "56",
      "timeSeconds": 19.07412338256836
    },
    {
      "markName": "57",
      "timeSeconds": 19.524417877197266
    },
    {
      "markName": "58",
      "timeSeconds": 19.67941665649414
    },
    {
      "markName": "59",
      "timeSeconds": 20.04895782470703
    },
    {
      "markName": "60",
      "timeSeconds": 20.1839599609375
    },
    {
      "markName": "61",
      "timeSeconds": 20.372333526611328
    },
    {
      "markName": "62",
      "timeSeconds": 21.04708480834961
    },
    {
      "markName": "63",
      "timeSeconds": 21.157085418701172
    },
    {
      "markName": "64",
      "timeSeconds": 21.2570858001709
    },
    {
      "markName": "65",
      "timeSeconds": 21.866252899169922
    },
    {
      "markName": "66",
      "timeSeconds": 23.539962768554688
    },
    {
      "markName": "67",
      "timeSeconds": 23.744962692260742
    },
    {
      "markName": "68",
      "timeSeconds": 23.909963607788086
    },
    {
      "markName": "69",
      "timeSeconds": 24.317838668823242
    },
    {
      "markName": "70",
      "timeSeconds": 24.50783920288086
    },
    {
      "markName": "71",
      "timeSeconds": 25.172964096069336
    },
    {
      "markName": "72",
      "timeSeconds": 25.337963104248047
    },
    {
      "markName": "73",
      "timeSeconds": 25.53304672241211
    },
    {
      "markName": "74",
      "timeSeconds": 25.673046112060547
    },
    {
      "markName": "75",
      "timeSeconds": 26.098255157470703
    },
    {
      "markName": "76",
      "timeSeconds": 26.248254776000977
    },
    {
      "markName": "77",
      "timeSeconds": 26.552879333496094
    },
    {
      "markName": "78",
      "timeSeconds": 26.97346305847168
    },
    {
      "markName": "79",
      "timeSeconds": 27.318588256835938
    },
    {
      "markName": "80",
      "timeSeconds": 27.532920837402344
    },
    {
      "markName": "81",
      "timeSeconds": 28.027921676635742
    },
    {
      "markName": "82",
      "timeSeconds": 28.137922286987305
    },
    {
      "markName": "83",
      "timeSeconds": 28.697505950927734
    },
    {
      "markName": "84",
      "timeSeconds": 29.345006942749023
    },
    {
      "markName": "85",
      "timeSeconds": 30.153881072998047
    },
    {
      "markName": "86",
      "timeSeconds": 30.85875701904297
    },
    {
      "markName": "87",
      "timeSeconds": 31.558673858642578
    },
    {
      "markName": "88",
      "timeSeconds": 31.6336727142334
    },
    {
      "markName": "89",
      "timeSeconds": 31.882965087890625
    },
    {
      "markName": "90",
      "timeSeconds": 32.71529769897461
    },
    {
      "markName": "91",
      "timeSeconds": 33.26346206665039
    },
    {
      "markName": "92",
      "timeSeconds": 33.801048278808594
    },
    {
      "markName": "93",
      "timeSeconds": 33.97604751586914
    },
    {
      "markName": "94",
      "timeSeconds": 34.09579849243164
    },
    {
      "markName": "95",
      "timeSeconds": 34.707130432128906
    },
    {
      "markName": "96",
      "timeSeconds": 35.788753509521484
    },
    {
      "markName": "97",
      "timeSeconds": 36.04900360107422
    },
    {
      "markName": "98",
      "timeSeconds": 36.36900329589844
    },
    {
      "markName": "99",
      "timeSeconds": 36.53421401977539
    },
    {
      "markName": "100",
      "timeSeconds": 36.62921142578125
    },
    {
      "markName": "101",
      "timeSeconds": 36.86421203613281
    },
    {
      "markName": "102",
      "timeSeconds": 36.984214782714844
    },
    {
      "markName": "103",
      "timeSeconds": 37.46892166137695
    },
    {
      "markName": "104",
      "timeSeconds": 38.04133987426758
    },
    {
      "markName": "105",
      "timeSeconds": 38.532630920410156
    },
    {
      "markName": "106",
      "timeSeconds": 38.61763000488281
    },
    {
      "markName": "107",
      "timeSeconds": 39.0852165222168
    },
    {
      "markName": "108",
      "timeSeconds": 39.184547424316406
    },
    {
      "markName": "109",
      "timeSeconds": 39.23954772949219
    },
    {
      "markName": "110",
      "timeSeconds": 39.40454864501953
    },
    {
      "markName": "111",
      "timeSeconds": 40.76580047607422
    },
    {
      "markName": "112",
      "timeSeconds": 41.05080032348633
    },
    {
      "markName": "113",
      "timeSeconds": 41.570926666259766
    },
    {
      "markName": "114",
      "timeSeconds": 41.62092590332031
    },
    {
      "markName": "115",
      "timeSeconds": 42.18775939941406
    }
  ]
}