{
  "text": "Selon une analyse approfondie réalisée par l'agence d'urbanisation de la région d'Angers, la périurbanisation gagne du terrain. Ce terme un peu technique désigne l'installation à la compagne de personnes qui travaillent en zone urbaine et y reviennent pour différentes activités et services. L'agence mène actuellement une étude sociologique pour mieux comprendre ce qui pousse les habitants à s'éloigner des métropoles. Leurs motivations correspondant souvent au désir d'accéder à la propriété ou de trouver un logement adapté lorsque la famille s'agrandit. Quelle est l'une des caractéristiques des périurbains » ?",
  "words": [
    "Selon",
    "une",
    "analyse",
    "approfondie",
    "réalisée",
    "par",
    "l&apos;agence",
    "d&apos;urbanisation",
    "de",
    "la",
    "région",
    "d&apos;Angers,",
    "la",
    "périurbanisation",
    "gagne",
    "du",
    "terrain.",
    "Ce",
    "terme",
    "un",
    "peu",
    "technique",
    "désigne",
    "l&apos;installation",
    "à",
    "la",
    "compagne",
    "de",
    "personnes",
    "qui",
    "travaillent",
    "en",
    "zone",
    "urbaine",
    "et",
    "y",
    "reviennent",
    "pour",
    "différentes",
    "activités",
    "et",
    "services.",
    "L&apos;agence",
    "mène",
    "actuellement",
    "une",
    "étude",
    "sociologique",
    "pour",
    "mieux",
    "comprendre",
    "ce",
    "qui",
    "pousse",
    "les",
    "habitants",
    "à",
    "s&apos;éloigner",
    "des",
    "métropoles.",
    "Leurs",
    "motivations",
    "correspondant",
    "souvent",
    "au",
    "désir",
    "d&apos;accéder",
    "à",
    "la",
    "propriété",
    "ou",
    "de",
    "trouver",
    "un",
    "logement",
    "adapté",
    "lorsque",
    "la",
    "famille",
    "s&apos;agrandit.",
    "Quelle",
    "est",
    "l&apos;une",
    "des",
    "caractéristiques",
    "des",
    "périurbains",
    "»",
    "?"
  ],
  "timepoints": [
    {
      "markName": "0",
      "timeSeconds": 0.014999999664723873
    },
    {
      "markName": "1",
      "timeSeconds": 0.4048333168029785
    },
    {
      "markName": "2",
      "timeSeconds": 0.5348333120346069
    },
    {
      "markName": "3",
      "timeSeconds": 1.0148333311080933
    },
    {
      "markName": "4",
      "timeSeconds": 1.737208366394043
    },
    {
      "markName": "5",
      "timeSeconds": 2.2806668281555176
    },
    {
      "markName": "6",
      "timeSeconds": 2.500666618347168
    },
    {
      "markName": "7",
      "timeSeconds": 2.9161667823791504
    },
    {
      "markName": "8",
      "timeSeconds": 3.8193747997283936
    },
    {
      "markName": "9",
      "timeSeconds": 3.9215831756591797
    },
    {
      "markName": "10",
      "timeSeconds": 4.021583557128906
    },
    {
      "markName": "11",
      "timeSeconds": 4.426541805267334
    },
    {
      "markName": "12",
      "timeSeconds": 5.2148332595825195
    },
    {
      "markName": "13",
      "timeSeconds": 5.334833145141602
    },
    {
      "markName": "14",
      "timeSeconds": 6.543165683746338
    },
    {
      "markName": "15",
      "timeSeconds": 6.834498405456543
    },
    {
      "markName": "16",
      "timeSeconds": 6.964498519897461
    },
    {
      "markName": "17",
      "timeSeconds": 8.231331825256348
    },
    {
      "markName": "18",
      "timeSeconds": 8.401331901550293
    },
    {
      "markName": "19",
      "timeSeconds": 8.716206550598145
    },
    {
      "markName": "20",
      "timeSeconds": 8.811206817626953
    },
    {
      "markName": "21",
      "timeSeconds": 8.971206665039062
    },
    {
      "markName": "22",
      "timeSeconds": 9.471122741699219
    },
    {
      "markName": "23",
      "timeSeconds": 9.925872802734375
    },
    {
      "markName": "24",
      "timeSeconds": 10.751373291015625
    },
    {
      "markName": "25",
      "timeSeconds": 10.79637336730957
    },
    {
      "markName": "26",
      "timeSeconds": 10.891373634338379
    },
    {
      "markName": "27",
      "timeSeconds": 11.376123428344727
    },
    {
      "markName": "28",
      "timeSeconds": 11.496124267578125
    },
    {
      "markName": "29",
      "timeSeconds": 12.069165229797363
    },
    {
      "markName": "30",
      "timeSeconds": 12.239165306091309
    },
    {
      "markName": "31",
      "timeSeconds": 12.660998344421387
    },
    {
      "markName": "32",
      "timeSeconds": 12.77599811553955
    },
    {
      "markName": "33",
      "timeSeconds": 13.02137279510498
    },
    {
      "markName": "34",
      "timeSeconds": 13.52178955078125
    },
    {
      "markName": "35",
      "timeSeconds": 13.616788864135742
    },
    {
      "markName": "36",
      "timeSeconds": 13.731955528259277
    },
    {
      "markName": "37",
      "timeSeconds": 14.17703914642334
    },
    {
      "markName": "38",
      "timeSeconds": 14.387039184570312
    },
    {
      "markName": "39",
      "timeSeconds": 15.041497230529785
    },
    {
      "markName": "40",
      "timeSeconds": 15.64828872680664
    },
    {
      "markName": "41",
      "timeSeconds": 15.713289260864258
    },
    {
      "markName": "42",
      "timeSeconds": 17.250789642333984
    },
    {
      "markName": "43",
      "timeSeconds": 17.795623779296875
    },
    {
      "markName": "44",
      "timeSeconds": 18.022748947143555
    },
    {
      "markName": "45",
      "timeSeconds": 18.70087432861328
    },
    {
      "markName": "46",
      "timeSeconds": 18.840248107910156
    },
    {
      "markName": "47",
      "timeSeconds": 19.140249252319336
    },
    {
      "markName": "48",
      "timeSeconds": 20.00287437438965
    },
    {
      "markName": "49",
      "timeSeconds": 20.237873077392578
    },
    {
      "markName": "50",
      "timeSeconds": 20.433748245239258
    },
    {
      "markName": "51",
      "timeSeconds": 21.109291076660156
    },
    {
      "markName": "52",
      "timeSeconds": 21.293289184570312
    },
    {
      "markName": "53",
      "timeSeconds": 21.458290100097656
    },
    {
      "markName": "54",
      "timeSeconds": 21.78829002380371
    },
    {
      "markName": "55",
      "timeSeconds": 21.991914749145508
    },
    {
      "markName": "56",
      "timeSeconds": 22.45724868774414
    },
    {
      "markName": "57",
      "timeSeconds": 22.507247924804688
    },
    {
      "markName": "58",
      "timeSeconds": 23.093873977661133
    },
    {
      "markName": "59",
      "timeSeconds": 23.218873977661133
    },
    {
      "markName": "60",
      "timeSeconds": 24.8071231842041
    },
    {
      "markName": "61",
      "timeSeconds": 25.007123947143555
    },
    {
      "markName": "62",
      "timeSeconds": 25.735248565673828
    },
    {
      "markName": "63",
      "timeSeconds": 26.51908302307129
    },
    {
      "markName": "64",
      "timeSeconds": 26.964874267578125
    },
    {
      "markName": "65",
      "timeSeconds": 27.039873123168945
    },
    {
      "markName": "66",
      "timeSeconds": 27.491456985473633
    },
    {
      "markName": "67",
      "timeSeconds": 28.049541473388672
    },
    {
      "markName": "68",
      "timeSeconds": 28.11954116821289
    },
    {
      "markName": "69",
      "timeSeconds": 28.219539642333984
    },
    {
      "markName": "70",
      "timeSeconds": 28.986082077026367
    },
    {
      "markName": "71",
      "timeSeconds": 29.112747192382812
    },
    {
      "markName": "72",
      "timeSeconds": 29.242748260498047
    },
    {
      "markName": "73",
      "timeSeconds": 29.62383270263672
    },
    {
      "markName": "74",
      "timeSeconds": 29.723831176757812
    },
    {
      "markName": "75",
      "timeSeconds": 30.186622619628906
    },
    {
      "markName": "76",
      "timeSeconds": 30.70203971862793
    },
    {
      "markName": "77",
      "timeSeconds": 31.065998077392578
    },
    {
      "markName": "78",
      "timeSeconds": 31.160999298095703
    },
    {
      "markName": "79",
      "timeSeconds": 31.521831512451172
    },
    {
      "markName": "80",
      "timeSeconds": 33.026790618896484
    },
    {
      "markName": "81",
      "timeSeconds": 33.23179244995117
    },
    {
      "markName": "82",
      "timeSeconds": 33.30179214477539
    },
    {
      "markName": "83",
      "timeSeconds": 33.577083587646484
    },
    {
      "markName": "84",
      "timeSeconds": 33.68708419799805
    },
    {
      "markName": "85",
      "timeSeconds": 34.60300064086914
    },
    {
      "markName": "86",
      "timeSeconds": 34.75299835205078
    },
    {
      "markName": "87",
      "timeSeconds": 35.46537399291992
    },
    {
      "markName": "88",
      "timeSeconds": 35.46537399291992
    }
  ]
}